frasco_slack.py
setup.py
frasco_slack.egg-info/PKG-INFO
frasco_slack.egg-info/SOURCES.txt
frasco_slack.egg-info/dependency_links.txt
frasco_slack.egg-info/not-zip-safe
frasco_slack.egg-info/requires.txt
frasco_slack.egg-info/top_level.txt