Metadata-Version: 1.0
Name: frasco-slack
Version: 0.1.1
Summary: Create Slack integration in Frasco
Home-page: http://github.com/frascoweb/frasco-slack
Author: Maxime Bouroumeau-Fuseau
Author-email: maxime.bouroumeau@gmail.com
License: MIT
Platform: any
